{
  "pageContent": "poppermost), et moi « Exact ! » Et on se sentait mieux »[52]. Par ailleurs, nostalgique de cette époque « cuir », on entend aussi John Lennon expliquer dans le disque Anthology 1 : « Ce que nous avons fait de meilleur n’a jamais été enregistré. Nous étions des performers, nous jouions du pur rock (straight rock) dans les salles de danse (dance halls), à Liverpool et à Hambourg, et ce que nous produisions était fantastique. Il n’y avait personne pour nous égaler en Grande-Bretagne (There was",
  "metadata": {
    "source": "https://fr.wikipedia.org/wiki/The_Beatles",
    "loc": {
      "lines": {
        "from": 108,
        "to": 108
      }
    }
  }
}