{
  "pageContent": "5 mars 1996\tReal Love / Baby's in Black\n19 mars 1996\tAnthology 2\tDouble CD\n29 octobre 1996\tAnthology 3\n18 novembre 2003\tLet It Be… Naked / Fly on the Wall\tDouble CD\n20 novembre 2006\tLove\tCD / Double CD\n11 novembre 2013\tOn Air - Live at the BBC Volume 2\tDouble CD\n17 décembre 2013\tThe Beatles Bootleg Recordings 1963\tTéléchargement\n9 septembre 2016\tThe Beatles: Live at the Hollywood Bowl [n 21]\tCD\n26 mai 2017\tSgt. Pepper’s Lonely Hearts Club Band",
  "metadata": {
    "source": "https://fr.wikipedia.org/wiki/Discographie_des_Beatles",
    "loc": {
      "lines": {
        "from": 855,
        "to": 863
      }
    }
  }
}