{
  "pageContent": "↑ (en) Mike Fleming Jr, « Sam Mendes, Sony & Apple Corps Set Four Beatles Theatrical Movies On Paul McCartney, John Lennon, George Harrison & Ringo Starr », Deadline Hollywood,‎ 20 février 2024 (lire en ligne, consulté le 20 février 2024).\n↑ M. G., « Yesterday : Quand Danny Boyle imagine un monde sans les Beatles », Paris Match,‎ 13 février 2019 (lire en ligne, consulté le 15 février 2019).\nVoir aussi\nOuvrages francophones",
  "metadata": {
    "source": "https://fr.wikipedia.org/wiki/The_Beatles",
    "loc": {
      "lines": {
        "from": 1465,
        "to": 1468
      }
    }
  }
}