{
  "pageContent": "seront enregistrées par EMI, qui financera le tout. Le label sera le propriétaire des enregistrements, mais ne donnera aucune avance sur les redevances (fixées à 1 penny par 45 tours vendu, sur 85 % des ventes)[i]. Le contrat a une durée de 4 ans pour le groupe, mais d’un an pour EMI, renouvelable à chaque anniversaire, et est valable pour le monde entier, mais avec des redevances réduites de moitié par rapport à celles perçues en Angleterre. Dans les faits, si par « miracle » le groupe vendait",
  "metadata": {
    "source": "https://fr.wikipedia.org/wiki/The_Beatles",
    "loc": {
      "lines": {
        "from": 128,
        "to": 128
      }
    }
  }
}